cnspy_csv2dataframe/CSV2DataFrame.py
cnspy_csv2dataframe/PosOrientCovCSV2DataFrame.py
cnspy_csv2dataframe/PosOrientWithCov2DataFrame.py
cnspy_csv2dataframe/PosOrientWithCovTyped2DataFrame.py
cnspy_csv2dataframe/PoseErrorStamped2DataFrame.py
cnspy_csv2dataframe/PoseTypedStamped2DataFrame.py
cnspy_csv2dataframe/PoseWithCov2DataFrame.py
cnspy_csv2dataframe/PoseWithCovTyped2DataFrame.py
cnspy_csv2dataframe/TUMCSV2DataFrame.py
cnspy_csv2dataframe/TimestampCSV2DataFrame.py
cnspy_csv2dataframe/__init__.py
test/__init__.py
test/test_CSV2DataFrame.py
test/test_PosOrientWithCov2DataFrame.py
test/test_PosOrientWithCovTyped2DataFrame.py
test/test_PoseWithCov2DataFrame.py
test/test_PoseWithCovTyped2DataFrame.py
test/test_TUMCSV2DataFrame.py
test/test_TimestampCSV2DataFrame.py
cnspy_csv2dataframe-0.2.3.dist-info/LICENCE
cnspy_csv2dataframe-0.2.3.dist-info/METADATA
cnspy_csv2dataframe-0.2.3.dist-info/WHEEL
cnspy_csv2dataframe-0.2.3.dist-info/top_level.txt
cnspy_csv2dataframe-0.2.3.dist-info/RECORD
